myria3d/__init__.py
myria3d/_version.py
myria3d/predict.py
myria3d/train.py
myria3d-3.8.4.dist-info/LICENSE
myria3d-3.8.4.dist-info/METADATA
myria3d-3.8.4.dist-info/WHEEL
myria3d-3.8.4.dist-info/top_level.txt
myria3d-3.8.4.dist-info/RECORD
