Metadata-Version: 2.1
Name: myria3d
Version: 3.8.4
Summary: Deep Learning for the Semantic Segmentation of Aerial Lidar Point Clouds
Author-email: Charles GAYDON <charles.gaydon@gmail.com>
Maintainer: Michel DAAB
Maintainer-email: Charles GAYDON <charles.gaydon@gmail.com>, Léa VAUCHIER <lea.vauchier@ign.fr>
License: BSD 3-Clause License
Project-URL: Documentation, https://ignf.github.io/myria3d/
Project-URL: Repository, https://github.com/IGNF/myria3d
Project-URL: Issues, https://github.com/IGNF/myria3d/issues
Project-URL: Changelog, https://github.com/IGNF/myria3d/blob/main/CHANGELOG.md
License-File: LICENSE
